dot_sync/__init__.py
dot_sync/cli.py
dot_sync/dot_sync.py
dot_sync-0.1.0.dist-info/DESCRIPTION.rst
dot_sync-0.1.0.dist-info/METADATA
dot_sync-0.1.0.dist-info/RECORD
dot_sync-0.1.0.dist-info/WHEEL
dot_sync-0.1.0.dist-info/entry_points.txt
dot_sync-0.1.0.dist-info/metadata.json
dot_sync-0.1.0.dist-info/top_level.txt
