Metadata-Version: 2.0
Name: dot-sync
Version: 0.1.0
Summary: A tool for syncing dotfiles between linux machines
Home-page: https://github.com/carlba/dot_sync
Author: Carl Bäckström
Author-email: genzorg@gmail.com
License: MIT license
Keywords: dot_sync
Platform: UNKNOWN
Classifier: Development Status :: 2 - Pre-Alpha
Classifier: Intended Audience :: Developers
Classifier: License :: OSI Approved :: MIT License
Classifier: Natural Language :: English
Classifier: Programming Language :: Python :: 2
Classifier: Programming Language :: Python :: 2.7
Classifier: Programming Language :: Python :: 3
Classifier: Programming Language :: Python :: 3.5
Requires-Dist: Click (>=6.7)
Requires-Dist: pathlib2 (>=2.3.0)
Requires-Dist: scandir (>=1.5)
Requires-Dist: sh (>=1.12.14)
